odoo10_addon_partner_socialmedia-10.0.1.0.0.99.dev2-py2.7-nspkg.pth
odoo/addons/partner_socialmedia/README.rst
odoo/addons/partner_socialmedia/__init__.py
odoo/addons/partner_socialmedia/__manifest__.py
odoo/addons/partner_socialmedia/i18n/partner_socialmedia.pot
odoo/addons/partner_socialmedia/models/__init__.py
odoo/addons/partner_socialmedia/models/res_partner.py
odoo/addons/partner_socialmedia/static/description/icon.png
odoo/addons/partner_socialmedia/views/res_partner_view.xml
odoo10_addon_partner_socialmedia-10.0.1.0.0.99.dev2.dist-info/METADATA
odoo10_addon_partner_socialmedia-10.0.1.0.0.99.dev2.dist-info/RECORD
odoo10_addon_partner_socialmedia-10.0.1.0.0.99.dev2.dist-info/WHEEL
odoo10_addon_partner_socialmedia-10.0.1.0.0.99.dev2.dist-info/namespace_packages.txt
odoo10_addon_partner_socialmedia-10.0.1.0.0.99.dev2.dist-info/top_level.txt
